tsmock.py
tsmock-0.1.2.dist-info/WHEEL
tsmock-0.1.2.dist-info/METADATA
tsmock-0.1.2.dist-info/RECORD
